lang_id_local.py
lang_id_local_python.py
lang_id_transform.py
lang_id_transform_python.py
lang_models.py
nlp.py
dpk_lang_id_transform_python-0.2.0.dist-info/METADATA
dpk_lang_id_transform_python-0.2.0.dist-info/WHEEL
dpk_lang_id_transform_python-0.2.0.dist-info/top_level.txt
dpk_lang_id_transform_python-0.2.0.dist-info/RECORD
